Metadata-Version: 2.1
Name: wagtailpolls-ng
Version: 0.5.3
Summary: A polling plugin for the Wagtail CMS
Home-page: https://github.com/frague59/wagtailpolls
Author: Takeflight
Author-email: liam@takeflight.com.au
License: BSD License
Platform: UNKNOWN
Classifier: Environment :: Web Environment
Classifier: Intended Audience :: Developers
Classifier: Development Status :: 4 - Beta
Classifier: Operating System :: OS Independent
Classifier: Environment :: Web Environment
Classifier: Programming Language :: Python
Classifier: Programming Language :: Python :: 3.7
Classifier: Programming Language :: Python :: 3.8
Classifier: Framework :: Django :: 2.0
Classifier: Framework :: Django :: 2.1
Classifier: License :: OSI Approved :: BSD License
Requires-Dist: wagtail (>=2.5)
Requires-Dist: django-ipware
Requires-Dist: django
